fit_tracker/__init__.py
fit_tracker/indexes.py
fit_tracker/parsers.py
fit_tracker/trackers.py
fit_tracker-0.0.2.dist-info/LICENSE
fit_tracker-0.0.2.dist-info/METADATA
fit_tracker-0.0.2.dist-info/WHEEL
fit_tracker-0.0.2.dist-info/top_level.txt
fit_tracker-0.0.2.dist-info/RECORD
