Metadata-Version: 2.1
Name: fit-tracker
Version: 0.0.2
Summary: A lightweight experiment tracker for numerical optimization problems.
Home-page: https://github.com/atraders/fit-tracker
Author: @genziano
License: UNKNOWN
Keywords: ml,operation research,optimization,logging
Platform: UNKNOWN
Classifier: Development Status :: 3 - Alpha
Classifier: Programming Language :: Python :: 3
Classifier: Programming Language :: Python :: 3.6
Classifier: Programming Language :: Python :: 3.7
Classifier: Programming Language :: Python :: 3.8
Classifier: Programming Language :: Python :: 3.9
Requires-Python: >=3.6, <4
Provides-Extra: dev
Requires-Dist: pylint ; extra == 'dev'
Requires-Dist: pytest ; extra == 'dev'
Requires-Dist: mypy ; extra == 'dev'
Requires-Dist: isort ; extra == 'dev'
